MANIFEST.in
README.md
setup.cfg
setup.py
cnregion/__init__.py
cnregion/_compat.py
cnregion/division.py
cnregion/exceptions.py
cnregion/region.py
cnregion/utils.py
cnregion.egg-info/PKG-INFO
cnregion.egg-info/SOURCES.txt
cnregion.egg-info/dependency_links.txt
cnregion.egg-info/requires.txt
cnregion.egg-info/top_level.txt
cnregion/data/deprecated_division.json
cnregion/data/deprecated_jd_division.json
cnregion/data/deprecated_jd_division_mappings.json
cnregion/data/division.json
cnregion/data/jd_division.json
cnregion/data/jd_division_mappings.json
test/test_cnregion.py