Metadata-Version: 1.1
Name: cnregion
Version: 0.1.0
Summary: China region utils
Home-page: https://github.com/xiachufang/cnregion
Author: cadl
Author-email: cadl@xiachufang.com
License: MIT
Keywords: china region
Platform: UNKNOWN
Classifier: Development Status :: 3 - Alpha
Classifier: License :: OSI Approved :: MIT License
Classifier: Natural Language :: Chinese (Simplified)
Classifier: Programming Language :: Python :: 2
Classifier: Programming Language :: Python :: 2.6
Classifier: Programming Language :: Python :: 2.7
Classifier: Programming Language :: Python :: 3.3
Classifier: Programming Language :: Python :: 3.4
